{
  "hash": "0211253242526573829101053111912213214201515162172181",
  "edition": 538,
  "date": 1668734965563,
  "attributes": [
    {
      "id": 2,
      "layer": "00_Background",
      "name": "02",
      "rarity": "original"
    },
    {
      "id": 1,
      "layer": "01_Background_Cloud",
      "name": "cloudbase",
      "rarity": "original"
    },
    {
      "id": 5,
      "layer": "02_Background_Effect",
      "name": "starry",
      "rarity": "original"
    },
    {
      "id": 2,
      "layer": "03_Tail",
      "name": "00_puff",
      "rarity": "original"
    },
    {
      "id": 2,
      "layer": "04_Torso",
      "name": "02",
      "rarity": "original"
    },
    {
      "id": 2,
      "layer": "05_Head",
      "name": "02",
      "rarity": "original"
    },
    {
      "id": 5,
      "layer": "06_Cheeks",
      "name": "whiskers",
      "rarity": "original"
    },
    {
      "id": 3,
      "layer": "07_Mouth",
      "name": "cutie",
      "rarity": "original"
    },
    {
      "id": 2,
      "layer": "08_Nose",
      "name": "none",
      "rarity": "original"
    },
    {
      "id": 10,
      "layer": "09_Eyes",
      "name": "mischievous",
      "rarity": "original"
    },
    {
      "id": 53,
      "layer": "10_Ears",
      "name": "02_02_batty",
      "rarity": "original"
    },
    {
      "id": 19,
      "layer": "11_Fluff",
      "name": "02_00_puff",
      "rarity": "original"
    },
    {
      "id": 2,
      "layer": "12_Face_Accessories",
      "name": "00_glasses",
      "rarity": "original"
    },
    {
      "id": 2,
      "layer": "13_Left Arm",
      "name": "02",
      "rarity": "original"
    },
    {
      "id": 20,
      "layer": "14_Paw_Pad",
      "name": "02_03_02_hearts",
      "rarity": "original"
    },
    {
      "id": 15,
      "layer": "15_Categories",
      "name": "03_drum",
      "rarity": "original"
    },
    {
      "id": 2,
      "layer": "16_Right Arm",
      "name": "02",
      "rarity": "original"
    },
    {
      "id": 2,
      "layer": "17_Wings",
      "name": "lil devil",
      "rarity": "original"
    },
    {
      "id": 1,
      "layer": "18_Foreground_Cloud",
      "name": "clouds",
      "rarity": "original"
    }
  ]
}