{
  "hash": "05112337045556477849110155116412513514551543165171181",
  "edition": 299,
  "date": 1668734960362,
  "attributes": [
    {
      "id": 5,
      "layer": "00_Background",
      "name": "05",
      "rarity": "original"
    },
    {
      "id": 1,
      "layer": "01_Background_Cloud",
      "name": "cloudbase",
      "rarity": "original"
    },
    {
      "id": 3,
      "layer": "02_Background_Effect",
      "name": "glow",
      "rarity": "original"
    },
    {
      "id": 70,
      "layer": "03_Tail",
      "name": "05_00_tapered",
      "rarity": "original"
    },
    {
      "id": 5,
      "layer": "04_Torso",
      "name": "05",
      "rarity": "original"
    },
    {
      "id": 5,
      "layer": "05_Head",
      "name": "05",
      "rarity": "original"
    },
    {
      "id": 4,
      "layer": "06_Cheeks",
      "name": "spiral",
      "rarity": "original"
    },
    {
      "id": 7,
      "layer": "07_Mouth",
      "name": "panic",
      "rarity": "original"
    },
    {
      "id": 4,
      "layer": "08_Nose",
      "name": "snuffy",
      "rarity": "original"
    },
    {
      "id": 1,
      "layer": "09_Eyes",
      "name": "alert",
      "rarity": "original"
    },
    {
      "id": 155,
      "layer": "10_Ears",
      "name": "05_01_fennec",
      "rarity": "original"
    },
    {
      "id": 64,
      "layer": "11_Fluff",
      "name": "05_01_swept",
      "rarity": "original"
    },
    {
      "id": 5,
      "layer": "12_Face_Accessories",
      "name": "00_specs",
      "rarity": "original"
    },
    {
      "id": 5,
      "layer": "13_Left Arm",
      "name": "05",
      "rarity": "original"
    },
    {
      "id": 55,
      "layer": "14_Paw_Pad",
      "name": "05_03_01_hearts",
      "rarity": "original"
    },
    {
      "id": 43,
      "layer": "15_Categories",
      "name": "08_digital_camera",
      "rarity": "original"
    },
    {
      "id": 5,
      "layer": "16_Right Arm",
      "name": "05",
      "rarity": "original"
    },
    {
      "id": 1,
      "layer": "17_Wings",
      "name": "cherub",
      "rarity": "original"
    },
    {
      "id": 1,
      "layer": "18_Foreground_Cloud",
      "name": "clouds",
      "rarity": "original"
    }
  ]
}