{
  "hash": "081123312348586574839141028011212113814891532168173181",
  "edition": 789,
  "date": 1668734971617,
  "attributes": [
    {
      "id": 8,
      "layer": "00_Background",
      "name": "08",
      "rarity": "original"
    },
    {
      "id": 1,
      "layer": "01_Background_Cloud",
      "name": "cloudbase",
      "rarity": "original"
    },
    {
      "id": 3,
      "layer": "02_Background_Effect",
      "name": "glow",
      "rarity": "original"
    },
    {
      "id": 123,
      "layer": "03_Tail",
      "name": "08_02_bushy",
      "rarity": "original"
    },
    {
      "id": 8,
      "layer": "04_Torso",
      "name": "08",
      "rarity": "original"
    },
    {
      "id": 8,
      "layer": "05_Head",
      "name": "08",
      "rarity": "original"
    },
    {
      "id": 5,
      "layer": "06_Cheeks",
      "name": "whiskers",
      "rarity": "original"
    },
    {
      "id": 4,
      "layer": "07_Mouth",
      "name": "demure",
      "rarity": "original"
    },
    {
      "id": 3,
      "layer": "08_Nose",
      "name": "round",
      "rarity": "original"
    },
    {
      "id": 14,
      "layer": "09_Eyes",
      "name": "sweet",
      "rarity": "original"
    },
    {
      "id": 280,
      "layer": "10_Ears",
      "name": "08_02_kitty",
      "rarity": "original"
    },
    {
      "id": 2,
      "layer": "11_Fluff",
      "name": "00_none",
      "rarity": "original"
    },
    {
      "id": 1,
      "layer": "12_Face_Accessories",
      "name": "00_bandaid",
      "rarity": "original"
    },
    {
      "id": 8,
      "layer": "13_Left Arm",
      "name": "08",
      "rarity": "original"
    },
    {
      "id": 89,
      "layer": "14_Paw_Pad",
      "name": "08_02_02_clubs",
      "rarity": "original"
    },
    {
      "id": 32,
      "layer": "15_Categories",
      "name": "06_green_controller",
      "rarity": "original"
    },
    {
      "id": 8,
      "layer": "16_Right Arm",
      "name": "08",
      "rarity": "original"
    },
    {
      "id": 3,
      "layer": "17_Wings",
      "name": "none",
      "rarity": "original"
    },
    {
      "id": 1,
      "layer": "18_Foreground_Cloud",
      "name": "clouds",
      "rarity": "original"
    }
  ]
}