{
  "hash": "07112239947576171819510224118712413714831533167171181",
  "edition": 682,
  "date": 1668734968900,
  "attributes": [
    {
      "id": 7,
      "layer": "00_Background",
      "name": "07",
      "rarity": "original"
    },
    {
      "id": 1,
      "layer": "01_Background_Cloud",
      "name": "cloudbase",
      "rarity": "original"
    },
    {
      "id": 2,
      "layer": "02_Background_Effect",
      "name": "cloudy",
      "rarity": "original"
    },
    {
      "id": 99,
      "layer": "03_Tail",
      "name": "07_00_curled",
      "rarity": "original"
    },
    {
      "id": 7,
      "layer": "04_Torso",
      "name": "07",
      "rarity": "original"
    },
    {
      "id": 7,
      "layer": "05_Head",
      "name": "07",
      "rarity": "original"
    },
    {
      "id": 1,
      "layer": "06_Cheeks",
      "name": "blush",
      "rarity": "original"
    },
    {
      "id": 1,
      "layer": "07_Mouth",
      "name": "cheerful",
      "rarity": "original"
    },
    {
      "id": 1,
      "layer": "08_Nose",
      "name": "blush",
      "rarity": "original"
    },
    {
      "id": 5,
      "layer": "09_Eyes",
      "name": "cautious",
      "rarity": "original"
    },
    {
      "id": 224,
      "layer": "10_Ears",
      "name": "07_00_droopy",
      "rarity": "original"
    },
    {
      "id": 87,
      "layer": "11_Fluff",
      "name": "07_00_bangs",
      "rarity": "original"
    },
    {
      "id": 4,
      "layer": "12_Face_Accessories",
      "name": "00_none",
      "rarity": "original"
    },
    {
      "id": 7,
      "layer": "13_Left Arm",
      "name": "07",
      "rarity": "original"
    },
    {
      "id": 83,
      "layer": "14_Paw_Pad",
      "name": "07_04_02_diamonds",
      "rarity": "original"
    },
    {
      "id": 33,
      "layer": "15_Categories",
      "name": "06_math_book",
      "rarity": "original"
    },
    {
      "id": 7,
      "layer": "16_Right Arm",
      "name": "07",
      "rarity": "original"
    },
    {
      "id": 1,
      "layer": "17_Wings",
      "name": "cherub",
      "rarity": "original"
    },
    {
      "id": 1,
      "layer": "18_Foreground_Cloud",
      "name": "clouds",
      "rarity": "original"
    }
  ]
}